Workbook

Sheet mapeamento dos emprestimos
D1: =SUBTOTAL(9,D3:D11) -> 80000 | F1: =SUM(F3:F10) -> 48 | H1: =SUM(M1:HF1) -> 109869.76 | J1: =SUM(J3:J10) -> 2121.23 | K1: =SUM(K3:K10) -> 42 | L1: =SUM(L3:L10) -> 0 | M1: =SUBTOTAL(9,M3:M13) -> 10171.95 | N1: =SUBTOTAL(9,N3:N13) -> 0 | O1: =SUBTOTAL(9,O3:O13) -> 2121.23 | P1: =SUBTOTAL(9,P3:P13) -> 2121.23 | Q1: =SUBTOTAL(9,Q3:Q13) -> 2121.23 | R1: =SUBTOTAL(9,R3:R13) -> 2121.23 | S1: =SUBTOTAL(9,S3:S13) -> 2121.23 | T1: =SUBTOTAL(9,T3:T13) -> 2121.23 | ... HF1: =SUBTOTAL(9,HF3:HF13) -> 0
A2: Credor | B2: Financiamento | C2: Tabela | D2: Valor Liquido | E2: tx | F2: N Parcela | G2: peso | H2: Primeira parcela | I2: Ultima Parcela | J2: Parcela estimada | K2: Parcelas Restantes | L2: Valor Total Parcelas | M2: 45434 | N2: 45465 | O2: 45495 | P2: 45526 | Q2: 45557 | R2: 45587 | S2: 45618 | T2: 45648 | U2: 45679 | V2: 45710 | W2: 45738 | X2: 45769 | Y2: 45799 | Z2: 45830 | AA2: 45860 | AB2: 45891 | AC2: 45922 | AD2: 45952 | AE2: 45983 | AF2: 46013 | AG2: 46044 | AH2: 46075 | AI2: 46103 | AJ2: 46134 | AK2: 46164 | AL2: 46195 | AM2: 46225 | AN2: 46256 | AO2: 46287 | AP2: 46317 | AQ2: 46348 | AR2: 46378 | AS2: 46409 | AT2: 46440 | AU2: 46468 | AV2: 46499 | AW2: 46529 | AX2: 46560 | AY2: 46590 | AZ2: 46621 | BA2: 46652 | BB2: 46682 | BC2: 46713 | BD2: 46743 | BE2: 46774 | BF2: 46805 | BG2: 46834 | BH2: 46865 | BI2: 46902
A3: Itau | B3: Pronampe | C3: Price | D3: 80000 | E3: 0,48%+Selic | F3: 48 | G3: =D3/$D$1 -> 1 | H3: 45533 | I3: 46902 | J3: 2121.23 | K3: 42 | M3: 10171.95 | O3: 2121.23 | P3: 2121.23 | Q3: 2121.23 | R3: 2121.23 | S3: 2121.23 | T3: 2121.23 | U3: 2121.23 | V3: 2121.23 | W3: 2121.23 | X3: 2121.23 | Y3: 2121.23 | Z3: 2121.23 | AA3: 2121.23 | AB3: 2121.23 | AC3: 2121.23 | AD3: 2121.23 | AE3: 2121.23 | AF3: 2121.23 | AG3: 2121.23 | AH3: 2121.23 | AI3: 2121.23 | AJ3: 2121.23 | AK3: 2121.23 | AL3: 2121.23 | AM3: 2121.23 | AN3: 2121.23 | AO3: 2121.23 | AP3: 2121.23 | AQ3: 2121.23 | AR3: 2121.23 | AS3: 2121.23 | AT3: 2121.23 | AU3: 2121.23 | AV3: 2121.23 | AW3: 2121.23 | AX3: 2121.23 | AY3: 2121.23 | AZ3: 2121.23 | BA3: 2121.23 | BB3: 2121.23 | BC3: 2121.23 | BD3: 2121.23 | BE3: 2121.23 | BF3: 2121.23 | BG3: 2121.23 | BH3: 2121.23 | BI3: 2121.23

Sheet SAC
G1: Valor Financiado | H1: 100000
G2: taxa de juros | I2: % ao ano | J2: SAC
G3: taxa de juros | H3: 0.02 | I3: % ao mês
G4: Correção | I4: % ao ano
G5: Correção | H5: =(1+$H$4)^(1/12)-1 -> 0 | I5: % ao mês
G6: Prazo de Pagamento | I6: anos
G7: Prazo de Pagamento | H7: 36 | I7: meses
G8: Carência | H8: 6 | I8: meses
D9: =SUM(D12:D129966) -> 0 | F9: =SUM(F12:F129966) -> 52970.395 | J9: =SUM(J12:J129966) -> 134201.02
A11: Vencimento | B11: Parcela | C11: Divida | D11: Correção | E11: Divida Corrigida | F11: Juros | G11: Amortização 1 | H11: Prestação | I11: Amortização 2 | J11: Total (Prestação + Amort 2) | K11: Saldo
A12: 45472 | B12: 1 | C12: =H1 -> 100000 | D12: =C12*$H$5 -> 0 | E12: =C12+D12 -> 100000 | F12: =E12*($H$3) -> 2000 | G12: =IF($H$8>=B12,0,(E12)/($H$7-($H$8))) -> 0 | H12: =IF($H$8>=B12,0,F12+G12) -> 0 | J12: =H12+I12 -> 0 | K12: =IF(G12<1,E12-G12-I12+F12,E12-G12-I12) -> 102000 | M12: =F12/$F$9 -> 0.037756939
A13: 45502 | B13: 2 | C13: =K12 -> 102000 | D13: =C13*$H$5 -> 0 | E13: =C13+D13 -> 102000 | F13: =E13*$H$3 -> 2040 | G13: =IF($H$8>=B13,0,(E13)/($H$7-(B12-$H$8))) -> 0 | H13: =IF($H$8>=B13,0,F13+G13) -> 0 | J13: =H13+I13 -> 0 | K13: =IF(G13<1,E13-G13-I13+F13,E13-G13-I13) -> 104040 | M13: =F13/$F$9 -> 0.038512078 | N13: =M13+M12 -> 0.076269017
A14: 45533 | B14: 3 | C14: =K13 -> 104040 | D14: =C14*$H$5 -> 0 | E14: =C14+D14 -> 104040 | F14: =E14*$H$3 -> 2080.8 | G14: =IF($H$8>=B14,0,(E14)/($H$7-(B13-$H$8))) -> 0 | H14: =IF($H$8>=B14,0,F14+G14) -> 0 | J14: =H14+I14 -> 0 | K14: =IF(G14<1,E14-G14-I14+F14,E14-G14-I14) -> 106120.8 | M14: =F14/$F$9 -> 0.03928232 | N14: =N13+M14 -> 0.11555134
A15: 45564 | B15: 4 | C15: =K14 -> 106120.8 | D15: =C15*$H$5 -> 0 | E15: =C15+D15 -> 106120.8 | F15: =E15*$H$3 -> 2122.416 | G15: =IF($H$8>=B15,0,(E15)/($H$7-(B14-$H$8))) -> 0 | H15: =IF($H$8>=B15,0,F15+G15) -> 0 | J15: =H15+I15 -> 0 | K15: =IF(G15<1,E15-G15-I15+F15,E15-G15-I15) -> 108243.22 | M15: =F15/$F$9 -> 0.040067966 | N15: =N14+M15 -> 0.1556193
A16: 45594 | B16: 5 | C16: =K15 -> 108243.22 | D16: =C16*$H$5 -> 0 | E16: =C16+D16 -> 108243.22 | F16: =E16*$H$3 -> 2164.8643 | G16: =IF($H$8>=B16,0,(E16)/($H$7-(B15-$H$8))) -> 0 | H16: =IF($H$8>=B16,0,F16+G16) -> 0 | J16: =H16+I16 -> 0 | K16: =IF(G16<1,E16-G16-I16+F16,E16-G16-I16) -> 110408.08 | M16: =F16/$F$9 -> 0.040869325 | N16: =N15+M16 -> 0.19648863
A17: 45625 | B17: 6 | C17: =K16 -> 110408.08 | D17: =C17*$H$5 -> 0 | E17: =C17+D17 -> 110408.08 | F17: =E17*$H$3 -> 2208.1616 | G17: =IF($H$8>=B17,0,(E17)/($H$7-(B16-$H$8))) -> 0 | H17: =IF($H$8>=B17,0,F17+G17) -> 0 | J17: =H17+I17 -> 0 | K17: =IF(G17<1,E17-G17-I17+F17,E17-G17-I17) -> 112616.24 | M17: =F17/$F$9 -> 0.041686712 | N17: =N16+M17 -> 0.23817534
A18: 45655 | B18: 7 | C18: =K17 -> 112616.24 | D18: =C18*$H$5 -> 0 | E18: =C18+D18 -> 112616.24 | F18: =E18*$H$3 -> 2252.3248 | G18: =IF($H$8>=B18,0,(E18)/($H$7-(B17-$H$8))) -> 3128.2289 | H18: =IF($H$8>=B18,0,F18+G18) -> 5380.5538 | J18: =H18+I18 -> 5380.5538 | K18: =IF(G18<1,E18-G18-I18+F18,E18-G18-I18) -> 109488.01 | M18: =F18/$F$9 -> 0.042520446 | N18: =N17+M18 -> 0.28069579
A19: 45686 | B19: 8 | C19: =K18 -> 109488.01 | D19: =C19*$H$5 -> 0 | E19: =C19+D19 -> 109488.01 | F19: =E19*$H$3 -> 2189.7603 | G19: =IF($H$8>=B19,0,(E19)/($H$7-(B18-$H$8))) -> 3128.2289 | H19: =IF($H$8>=B19,0,F19+G19) -> 5317.9892 | J19: =H19+I19 -> 5317.9892 | K19: =IF(G19<1,E19-G19-I19+F19,E19-G19-I19) -> 106359.78 | M19: =F19/$F$9 -> 0.041339323 | N19: =N18+M19 -> 0.32203511
A20: 45716 | B20: 9 | C20: =K19 -> 106359.78 | D20: =C20*$H$5 -> 0 | E20: =C20+D20 -> 106359.78 | F20: =E20*$H$3 -> 2127.1957 | G20: =IF($H$8>=B20,0,(E20)/($H$7-(B19-$H$8))) -> 3128.2289 | H20: =IF($H$8>=B20,0,F20+G20) -> 5255.4246 | J20: =H20+I20 -> 5255.4246 | K20: =IF(G20<1,E20-G20-I20+F20,E20-G20-I20) -> 103231.56 | M20: =F20/$F$9 -> 0.040158199 | N20: =N19+M20 -> 0.36219331
A21: 45745 | B21: 10 | C21: =K20 -> 103231.56 | D21: =C21*$H$5 -> 0 | E21: =C21+D21 -> 103231.56 | F21: =E21*$H$3 -> 2064.6311 | G21: =IF($H$8>=B21,0,(E21)/($H$7-(B20-$H$8))) -> 3128.2289 | H21: =IF($H$8>=B21,0,F21+G21) -> 5192.86 | J21: =H21+I21 -> 5192.86 | K21: =IF(G21<1,E21-G21-I21+F21,E21-G21-I21) -> 100103.33 | M21: =F21/$F$9 -> 0.038977076 | N21: =N20+M21 -> 0.40117038
A22: 45776 | B22: 11 | C22: =K21 -> 100103.33 | D22: =C22*$H$5 -> 0 | E22: =C22+D22 -> 100103.33 | F22: =E22*$H$3 -> 2002.0665 | G22: =IF($H$8>=B22,0,(E22)/($H$7-(B21-$H$8))) -> 3128.2289 | H22: =IF($H$8>=B22,0,F22+G22) -> 5130.2955 | J22: =H22+I22 -> 5130.2955 | K22: =IF(G22<1,E22-G22-I22+F22,E22-G22-I22) -> 96975.097 | M22: =F22/$F$9 -> 0.037795952 | N22: =N21+M22 -> 0.43896634
A23: 45806 | B23: 12 | C23: =K22 -> 96975.097 | D23: =C23*$H$5 -> 0 | E23: =C23+D23 -> 96975.097 | F23: =E23*$H$3 -> 1939.5019 | G23: =IF($H$8>=B23,0,(E23)/($H$7-(B22-$H$8))) -> 3128.2289 | H23: =IF($H$8>=B23,0,F23+G23) -> 5067.7309 | J23: =H23+I23 -> 5067.7309 | K23: =IF(G23<1,E23-G23-I23+F23,E23-G23-I23) -> 93846.868 | M23: =F23/$F$9 -> 0.036614829 | N23: =N22+M23 -> 0.47558116
A24: 45837 | B24: 13 | C24: =K23 -> 93846.868 | D24: =C24*$H$5 -> 0 | E24: =C24+D24 -> 93846.868 | F24: =E24*$H$3 -> 1876.9374 | G24: =IF($H$8>=B24,0,(E24)/($H$7-(B23-$H$8))) -> 3128.2289 | H24: =IF($H$8>=B24,0,F24+G24) -> 5005.1663 | J24: =H24+I24 -> 5005.1663 | K24: =IF(G24<1,E24-G24-I24+F24,E24-G24-I24) -> 90718.639 | M24: =F24/$F$9 -> 0.035433705 | N24: =N23+M24 -> 0.51101487
A25: 45867 | B25: 14 | C25: =K24 -> 90718.639 | D25: =C25*$H$5 -> 0 | E25: =C25+D25 -> 90718.639 | F25: =E25*$H$3 -> 1814.3728 | G25: =IF($H$8>=B25,0,(E25)/($H$7-(B24-$H$8))) -> 3128.2289 | H25: =IF($H$8>=B25,0,F25+G25) -> 4942.6017 | J25: =H25+I25 -> 4942.6017 | K25: =IF(G25<1,E25-G25-I25+F25,E25-G25-I25) -> 87590.41 | M25: =F25/$F$9 -> 0.034252582 | N25: =N24+M25 -> 0.54526745
... A47: 46536 | B47: 36 | C47: =K46 -> 21897.603 | D47: =C47*$H$5 -> 0 | E47: =C47+D47 -> 21897.603 | F47: =E47*$H$3 -> 437.95205 | G47: =IF($H$8>=B47,0,(E47)/($H$7-(B46-$H$8))) -> 3128.2289 | H47: =IF($H$8>=B47,0,F47+G47) -> 3566.181 | J47: =H47+I47 -> 3566.181 | K47: =IF(G47<1,E47-G47-I47+F47,E47-G47-I47) -> 18769.374 | M47: =F47/$F$9 -> 0.0082678645 | N47: =N46+M47 -> 1

Sheet PRICE
G1: Valor Financiado | H1: 80000 | L1: [PV * r * (1 + r)^n] / [(1 + r)^n - 1]
G2: taxa de juros | I2: % ao ano | J2: PRICE | M2: =E12*H3 -> 1056
G3: taxa de juros | H3: =0.48%+0.0084 -> 0.0132 | I3: % ao mês | M3: =(1+H3)^(H7)-1 -> 0.6033433
G4: Correção | I4: % ao ano | M4: =M2*M3 -> 637.13052
G5: Correção | H5: =(1+$H$4)^(1/12)-1 -> 0 | I5: % ao ano | M5: =(1+H3)^(H7)-1 -> 0.6033433
G6: Prazo de Pagamento | I6: anos | M6: =M4/M5 -> 1056
G7: Prazo de Pagamento | H7: 36 | I7: meses
G8: Carência | H8: 0 | I8: meses
D9: =SUM(D12:D129678) -> 0 | F9: =SUM(F12:F129678) -> 21024.904 | J9: =SUM(J12:J129678) -> 101024.9
A11: Vencimento | B11: Parcela | C11: Divida | D11: Correção | E11: Divida Corrigida | F11: Juros | G11: Amortização 1 | H11: Prestação | I11: Amortização 2 | J11: Total (Prestação + Amort 2) | K11: Saldo
A12: 43539 | B12: 1 | C12: =H1 -> 80000 | D12: =C12*$H$5 -> 0 | E12: =C12+D12 -> 80000 | F12: =E12*($H$3) -> 1056 | G12: =IF($H$8>=B12,0,H12-F12) -> 1750.2473 | H12: =IF(H8>0,0,($E$12*$H$3*(1+$H$3)^($H$7))/((1+$H$3)^($H$7)-1)) -> 2806.2473 | J12: =H12+I12 -> 2806.2473 | K12: =IF(G12<1,E12-G12-I12+F12,E12-G12-I12) -> 78249.753 | M12: =F12/$F$9 -> 0.05022615
A13: 43570 | B13: 2 | C13: =K12 -> 78249.753 | D13: =C13*$H$5 -> 0 | E13: =C13+D13 -> 78249.753 | F13: =E13*($H$3) -> 1032.8967 | G13: =IF($H$8>=B13,0,H13-F13) -> 1773.3506 | H13: =IF($H$8>B12,0,(E13*$H$3*(1+$H$3)^($H$7-(B12-$H$8))/((1+$H$3)^($H$7-(B12-$H$8))-1))) -> 2806.2473 | J13: =H13+I13 -> 2806.2473 | K13: =IF(G13<1,E13-G13-I13+F13,E13-G13-I13) -> 76476.402 | M13: =F13/$F$9 -> 0.049127298 | N13: =M13+M12 -> 0.099353448
A14: 43600 | B14: 3 | C14: =K13 -> 76476.402 | D14: =C14*$H$5 -> 0 | E14: =C14+D14 -> 76476.402 | F14: =E14*($H$3) -> 1009.4885 | G14: =IF($H$8>=B14,0,H14-F14) -> 1796.7588 | H14: =IF($H$8>B13,0,(E14*$H$3*(1+$H$3)^($H$7-(B13-$H$8))/((1+$H$3)^($H$7-(B13-$H$8))-1))) -> 2806.2473 | J14: =H14+I14 -> 2806.2473 | K14: =IF(G14<1,E14-G14-I14+F14,E14-G14-I14) -> 74679.643 | M14: =F14/$F$9 -> 0.048013941 | N14: =N13+M14 -> 0.14736739
A15: 43631 | B15: 4 | C15: =K14 -> 74679.643 | D15: =C15*$H$5 -> 0 | E15: =C15+D15 -> 74679.643 | F15: =E15*($H$3) -> 985.77129 | G15: =IF($H$8>=B15,0,H15-F15) -> 1820.4761 | H15: =IF($H$8>B14,0,(E15*$H$3*(1+$H$3)^($H$7-(B14-$H$8))/((1+$H$3)^($H$7-(B14-$H$8))-1))) -> 2806.2473 | J15: =H15+I15 -> 2806.2473 | K15: =IF(G15<1,E15-G15-I15+F15,E15-G15-I15) -> 72859.167 | M15: =F15/$F$9 -> 0.046885887 | N15: =N14+M15 -> 0.19425328
A16: 43661 | B16: 5 | C16: =K15 -> 72859.167 | D16: =C16*$H$5 -> 0 | E16: =C16+D16 -> 72859.167 | F16: =E16*($H$3) -> 961.74101 | G16: =IF($H$8>=B16,0,H16-F16) -> 1844.5063 | H16: =IF($H$8>B15,0,(E16*$H$3*(1+$H$3)^($H$7-(B15-$H$8))/((1+$H$3)^($H$7-(B15-$H$8))-1))) -> 2806.2473 | J16: =H16+I16 -> 2806.2473 | K16: =IF(G16<1,E16-G16-I16+F16,E16-G16-I16) -> 71014.661 | M16: =F16/$F$9 -> 0.045742943 | N16: =N15+M16 -> 0.23999622
A17: 43692 | B17: 6 | C17: =K16 -> 71014.661 | D17: =C17*$H$5 -> 0 | E17: =C17+D17 -> 71014.661 | F17: =E17*($H$3) -> 937.39352 | G17: =IF($H$8>=B17,0,H17-F17) -> 1868.8538 | H17: =IF($H$8>B16,0,(E17*$H$3*(1+$H$3)^($H$7-(B16-$H$8))/((1+$H$3)^($H$7-(B16-$H$8))-1))) -> 2806.2473 | J17: =H17+I17 -> 2806.2473 | K17: =IF(G17<1,E17-G17-I17+F17,E17-G17-I17) -> 69145.807 | M17: =F17/$F$9 -> 0.044584913 | N17: =N16+M17 -> 0.28458113
A18: 43723 | B18: 7 | C18: =K17 -> 69145.807 | D18: =C18*$H$5 -> 0 | E18: =C18+D18 -> 69145.807 | F18: =E18*($H$3) -> 912.72465 | G18: =IF($H$8>=B18,0,H18-F18) -> 1893.5227 | H18: =IF($H$8>B17,0,(E18*$H$3*(1+$H$3)^($H$7-(B17-$H$8))/((1+$H$3)^($H$7-(B17-$H$8))-1))) -> 2806.2473 | J18: =H18+I18 -> 2806.2473 | K18: =IF(G18<1,E18-G18-I18+F18,E18-G18-I18) -> 67252.284 | M18: =F18/$F$9 -> 0.043411596 | N18: =N17+M18 -> 0.32799273
A19: 43753 | B19: 8 | C19: =K18 -> 67252.284 | D19: =C19*$H$5 -> 0 | E19: =C19+D19 -> 67252.284 | F19: =E19*($H$3) -> 887.73015 | G19: =IF($H$8>=B19,0,H19-F19) -> 1918.5172 | H19: =IF($H$8>B18,0,(E19*$H$3*(1+$H$3)^($H$7-(B18-$H$8))/((1+$H$3)^($H$7-(B18-$H$8))-1))) -> 2806.2473 | J19: =H19+I19 -> 2806.2473 | K19: =IF(G19<1,E19-G19-I19+F19,E19-G19-I19) -> 65333.767 | M19: =F19/$F$9 -> 0.042222792 | N19: =N18+M19 -> 0.37021552
A20: 43784 | B20: 9 | C20: =K19 -> 65333.767 | D20: =C20*$H$5 -> 0 | E20: =C20+D20 -> 65333.767 | F20: =E20*($H$3) -> 862.40573 | G20: =IF($H$8>=B20,0,H20-F20) -> 1943.8416 | H20: =IF($H$8>B19,0,(E20*$H$3*(1+$H$3)^($H$7-(B19-$H$8))/((1+$H$3)^($H$7-(B19-$H$8))-1))) -> 2806.2473 | J20: =H20+I20 -> 2806.2473 | K20: =IF(G20<1,E20-G20-I20+F20,E20-G20-I20) -> 63389.926 | M20: =F20/$F$9 -> 0.041018295 | N20: =N19+M20 -> 0.41123381
A21: 43814 | B21: 10 | C21: =K20 -> 63389.926 | D21: =C21*$H$5 -> 0 | E21: =C21+D21 -> 63389.926 | F21: =E21*($H$3) -> 836.74702 | G21: =IF($H$8>=B21,0,H21-F21) -> 1969.5003 | H21: =IF($H$8>B20,0,(E21*$H$3*(1+$H$3)^($H$7-(B20-$H$8))/((1+$H$3)^($H$7-(B20-$H$8))-1))) -> 2806.2473 | J21: =H21+I21 -> 2806.2473 | K21: =IF(G21<1,E21-G21-I21+F21,E21-G21-I21) -> 61420.425 | M21: =F21/$F$9 -> 0.039797899 | N21: =N20+M21 -> 0.45103171
A22: 43845 | B22: 11 | C22: =K21 -> 61420.425 | D22: =C22*$H$5 -> 0 | E22: =C22+D22 -> 61420.425 | F22: =E22*($H$3) -> 810.74961 | G22: =IF($H$8>=B22,0,H22-F22) -> 1995.4977 | H22: =IF($H$8>B21,0,(E22*$H$3*(1+$H$3)^($H$7-(B21-$H$8))/((1+$H$3)^($H$7-(B21-$H$8))-1))) -> 2806.2473 | J22: =H22+I22 -> 2806.2473 | K22: =IF(G22<1,E22-G22-I22+F22,E22-G22-I22) -> 59424.927 | M22: =F22/$F$9 -> 0.038561394 | N22: =N21+M22 -> 0.48959311
A23: 43876 | B23: 12 | C23: =K22 -> 59424.927 | D23: =C23*$H$5 -> 0 | E23: =C23+D23 -> 59424.927 | F23: =E23*($H$3) -> 784.40904 | G23: =IF($H$8>=B23,0,H23-F23) -> 2021.8383 | H23: =IF($H$8>B22,0,(E23*$H$3*(1+$H$3)^($H$7-(B22-$H$8))/((1+$H$3)^($H$7-(B22-$H$8))-1))) -> 2806.2473 | J23: =H23+I23 -> 2806.2473 | K23: =IF(G23<1,E23-G23-I23+F23,E23-G23-I23) -> 57403.089 | M23: =F23/$F$9 -> 0.037308567 | N23: =N22+M23 -> 0.52690167
A24: 43905 | B24: 13 | C24: =K23 -> 57403.089 | D24: =C24*$H$5 -> 0 | E24: =C24+D24 -> 57403.089 | F24: =E24*($H$3) -> 757.72078 | G24: =IF($H$8>=B24,0,H24-F24) -> 2048.5266 | H24: =IF($H$8>B23,0,(E24*$H$3*(1+$H$3)^($H$7-(B23-$H$8))/((1+$H$3)^($H$7-(B23-$H$8))-1))) -> 2806.2473 | J24: =H24+I24 -> 2806.2473 | K24: =IF(G24<1,E24-G24-I24+F24,E24-G24-I24) -> 55354.563 | M24: =F24/$F$9 -> 0.036039202 | N24: =N23+M24 -> 0.56294088
A25: 43936 | B25: 14 | C25: =K24 -> 55354.563 | D25: =C25*$H$5 -> 0 | E25: =C25+D25 -> 55354.563 | F25: =E25*($H$3) -> 730.68023 | G25: =IF($H$8>=B25,0,H25-F25) -> 2075.5671 | H25: =IF($H$8>B24,0,(E25*$H$3*(1+$H$3)^($H$7-(B24-$H$8))/((1+$H$3)^($H$7-(B24-$H$8))-1))) -> 2806.2473 | J25: =H25+I25 -> 2806.2473 | K25: =IF(G25<1,E25-G25-I25+F25,E25-G25-I25) -> 53278.995 | M25: =F25/$F$9 -> 0.034753082 | N25: =N24+M25 -> 0.59769396
... A47: 44607 | B47: 36 | C47: =K46 -> 2769.6875 | D47: =C47*$H$5 -> 0 | E47: =C47+D47 -> 2769.6875 | F47: =E47*($H$3) -> 36.559875 | G47: =IF($H$8>=B47,0,H47-F47) -> 2769.6875 | H47: =IF($H$8>B46,0,(E47*$H$3*(1+$H$3)^($H$7-(B46-$H$8))/((1+$H$3)^($H$7-(B46-$H$8))-1))) -> 2806.2473 | J47: =H47+I47 -> 2806.2473 | K47: =IF(G47<1,E47-G47-I47+F47,E47-G47-I47) -> 2.0918378e-11 | M47: =F47/$F$9 -> 0.0017388842 | N47: =N46+M47 -> 1

Sheet comparação
E2: Diferença R$ | F2: =F5-E5 -> -31945.491
E3: Diferença % | F3: =F5/E5-1 -> -0.60308198
E5: =SUM(E7:E11000) -> 52970.395 | F5: =SUM(F7:F11000) -> 21024.904
C6: SAC | D6: PRICE | E6: SAC | F6: PRICE | G6: SAC | H6: PRICE
B7: 1 | C7: =SAC!C12 -> 100000 | D7: =PRICE!C12 -> 80000 | E7: =SAC!F12 -> 2000 | F7: =PRICE!F12 -> 1056 | G7: =SAC!J12 -> 0 | H7: =PRICE!J12 -> 2806.2473
B8: 2 | C8: =SAC!C13 -> 102000 | D8: =PRICE!C13 -> 78249.753 | E8: =SAC!F13 -> 2040 | F8: =PRICE!F13 -> 1032.8967 | G8: =SAC!J13 -> 0 | H8: =PRICE!J13 -> 2806.2473
B9: 3 | C9: =SAC!C14 -> 104040 | D9: =PRICE!C14 -> 76476.402 | E9: =SAC!F14 -> 2080.8 | F9: =PRICE!F14 -> 1009.4885 | G9: =SAC!J14 -> 0 | H9: =PRICE!J14 -> 2806.2473
B10: 4 | C10: =SAC!C15 -> 106120.8 | D10: =PRICE!C15 -> 74679.643 | E10: =SAC!F15 -> 2122.416 | F10: =PRICE!F15 -> 985.77129 | G10: =SAC!J15 -> 0 | H10: =PRICE!J15 -> 2806.2473
B11: 5 | C11: =SAC!C16 -> 108243.22 | D11: =PRICE!C16 -> 72859.167 | E11: =SAC!F16 -> 2164.8643 | F11: =PRICE!F16 -> 961.74101 | G11: =SAC!J16 -> 0 | H11: =PRICE!J16 -> 2806.2473
B12: 6 | C12: =SAC!C17 -> 110408.08 | D12: =PRICE!C17 -> 71014.661 | E12: =SAC!F17 -> 2208.1616 | F12: =PRICE!F17 -> 937.39352 | G12: =SAC!J17 -> 0 | H12: =PRICE!J17 -> 2806.2473
B13: 7 | C13: =SAC!C18 -> 112616.24 | D13: =PRICE!C18 -> 69145.807 | E13: =SAC!F18 -> 2252.3248 | F13: =PRICE!F18 -> 912.72465 | G13: =SAC!J18 -> 5380.5538 | H13: =PRICE!J18 -> 2806.2473
B14: 8 | C14: =SAC!C19 -> 109488.01 | D14: =PRICE!C19 -> 67252.284 | E14: =SAC!F19 -> 2189.7603 | F14: =PRICE!F19 -> 887.73015 | G14: =SAC!J19 -> 5317.9892 | H14: =PRICE!J19 -> 2806.2473
B15: 9 | C15: =SAC!C20 -> 106359.78 | D15: =PRICE!C20 -> 65333.767 | E15: =SAC!F20 -> 2127.1957 | F15: =PRICE!F20 -> 862.40573 | G15: =SAC!J20 -> 5255.4246 | H15: =PRICE!J20 -> 2806.2473
B16: 10 | C16: =SAC!C21 -> 103231.56 | D16: =PRICE!C21 -> 63389.926 | E16: =SAC!F21 -> 2064.6311 | F16: =PRICE!F21 -> 836.74702 | G16: =SAC!J21 -> 5192.86 | H16: =PRICE!J21 -> 2806.2473
B17: 11 | C17: =SAC!C22 -> 100103.33 | D17: =PRICE!C22 -> 61420.425 | E17: =SAC!F22 -> 2002.0665 | F17: =PRICE!F22 -> 810.74961 | G17: =SAC!J22 -> 5130.2955 | H17: =PRICE!J22 -> 2806.2473
B18: 12 | C18: =SAC!C23 -> 96975.097 | D18: =PRICE!C23 -> 59424.927 | E18: =SAC!F23 -> 1939.5019 | F18: =PRICE!F23 -> 784.40904 | G18: =SAC!J23 -> 5067.7309 | H18: =PRICE!J23 -> 2806.2473
... B42: 36 | C42: =SAC!C47 -> 21897.603 | D42: =PRICE!C47 -> 2769.6875 | E42: =SAC!F47 -> 437.95205 | F42: =PRICE!F47 -> 36.559875 | G42: =SAC!J47 -> 3566.181 | H42: =PRICE!J47 -> 2806.2473
